{
"listaNPC": [

{"ID":"c0x000","inaltime":"161","prenume":"Aria-Ancuta ","sex":"F","sociabilitate":"1","varsta":"41"}
,
{"ID":"c0x001","inaltime":"158","prenume":"Lidia","sex":"F","sociabilitate":"8","varsta":"28"}
,
{"ID":"c0x002","inaltime":"65","prenume":"Nicodim","sex":"M","sociabilitate":"3","varsta":"1"}
,
{"ID":"c0x003","inaltime":"157","prenume":"Dochia-Jasmina","sex":"F","sociabilitate":"9","varsta":"92"}
,
{"ID":"c0x004","inaltime":"170","prenume":"Ramona","sex":"F","sociabilitate":"5","varsta":"33"}
,
{"ID":"c0x005","inaltime":"164","prenume":"Gabi ","sex":"M","sociabilitate":"5","varsta":"45"}
,
{"ID":"c0x006","inaltime":"94","prenume":"Victoria","sex":"F","sociabilitate":"7","varsta":"2"}
,
{"ID":"c0x007","inaltime":"157","prenume":"Hannah","sex":"F","sociabilitate":"6","varsta":"70"}
,
{"ID":"c0x008","inaltime":"168","prenume":"Camil","sex":"M","sociabilitate":"3","varsta":"31"}
,
{"ID":"c0x009","inaltime":"177","prenume":"Emiliano","sex":"M","sociabilitate":"9","varsta":"20"}
,
{"ID":"c0x010","inaltime":"170","prenume":"Costache","sex":"M","sociabilitate":"5","varsta":"21"}
,
{"ID":"c0x011","inaltime":"170","prenume":"Valeriu","sex":"M","sociabilitate":"4","varsta":"61"}
,
{"ID":"c0x012","inaltime":"155","prenume":"Rada","sex":"F","sociabilitate":"1","varsta":"44"}
,
{"ID":"c0x013","inaltime":"155","prenume":"Ember","sex":"F","sociabilitate":"8","varsta":"76"}
,
{"ID":"c0x014","inaltime":"188","prenume":"Gherasim","sex":"M","sociabilitate":"6","varsta":"42"}
,
{"ID":"c0x015","inaltime":"184","prenume":"Jose","sex":"M","sociabilitate":"10","varsta":"50"}
,
{"ID":"c0x016","inaltime":"168","prenume":"Petronela-Esther-Marinela","sex":"F","sociabilitate":"4","varsta":"83"}
,
{"ID":"c0x017","inaltime":"173","prenume":"Marusia","sex":"F","sociabilitate":"4","varsta":"39"}
,
{"ID":"c0x018","inaltime":"180","prenume":"Samuel","sex":"M","sociabilitate":"6","varsta":"24"}
,
{"ID":"c0x019","inaltime":"159","prenume":"Mihaela ","sex":"F","sociabilitate":"8","varsta":"30"}
,
{"ID":"c0x020","inaltime":"176","prenume":"Antonie","sex":"M","sociabilitate":"8","varsta":"36"}
,
{"ID":"c0x021","inaltime":"155","prenume":"Hailey","sex":"F","sociabilitate":"4","varsta":"76"}
,
{"ID":"c0x022","inaltime":"166","prenume":"Kinsley-Tiberia-Florentina","sex":"F","sociabilitate":"8","varsta":"45"}
,
{"ID":"c0x023","inaltime":"171","prenume":"Valeriu-Dragos -Atanasio","sex":"M","sociabilitate":"4","varsta":"16"}
,
{"ID":"c0x024","inaltime":"168","prenume":"Eloise-Mihaela ","sex":"F","sociabilitate":"4","varsta":"32"}
,
{"ID":"c0x025","inaltime":"175","prenume":"Ludovic","sex":"M","sociabilitate":"6","varsta":"32"}
,
{"ID":"c0x026","inaltime":"161","prenume":"Glorita-Andrea","sex":"F","sociabilitate":"6","varsta":"97"}
,
{"ID":"c0x027","inaltime":"107","prenume":"Iorgu","sex":"M","sociabilitate":"6","varsta":"5"}
,
{"ID":"c0x028","inaltime":"166","prenume":"Lucy-Oana-Eloise","sex":"F","sociabilitate":"7","varsta":"41"}
,
{"ID":"c0x029","inaltime":"158","prenume":"Roberta","sex":"F","sociabilitate":"8","varsta":"53"}
,
{"ID":"c0x030","inaltime":"172","prenume":"Dionisie -Adrian","sex":"M","sociabilitate":"5","varsta":"98"}
,
{"ID":"c0x031","inaltime":"166","prenume":"Serenity","sex":"F","sociabilitate":"7","varsta":"33"}
,
{"ID":"c0x032","inaltime":"177","prenume":"Francisc ","sex":"M","sociabilitate":"3","varsta":"84"}
,
{"ID":"c0x033","inaltime":"166","prenume":"Alice","sex":"F","sociabilitate":"9","varsta":"59"}
,
{"ID":"c0x034","inaltime":"187","prenume":"Jackson","sex":"M","sociabilitate":"8","varsta":"94"}
,
{"ID":"c0x035","inaltime":"188","prenume":"Grigore","sex":"M","sociabilitate":"7","varsta":"99"}
,
{"ID":"c0x036","inaltime":"188","prenume":"Charles","sex":"M","sociabilitate":"4","varsta":"52"}
,
{"ID":"c0x037","inaltime":"166","prenume":"Marian","sex":"M","sociabilitate":"4","varsta":"420"}
,
{"ID":"c0x038","inaltime":"65","prenume":"Aleodor","sex":"M","sociabilitate":"3","varsta":"1"}
,
{"ID":"c0x039","inaltime":"159","prenume":"Vera","sex":"F","sociabilitate":"4","varsta":"23"}
,
{"ID":"c0x040","inaltime":"155","prenume":"Alice-Sadie","sex":"F","sociabilitate":"9","varsta":"54"}
,
{"ID":"c0x041","inaltime":"171","prenume":"Angelica","sex":"F","sociabilitate":"9","varsta":"56"}
,
{"ID":"c0x042","inaltime":"167","prenume":"Georgia-Paula","sex":"F","sociabilitate":"5","varsta":"59"}
,
{"ID":"c0x043","inaltime":"156","prenume":"Aliyah-Adelaida","sex":"F","sociabilitate":"3","varsta":"55"}
,
{"ID":"c0x044","inaltime":"167","prenume":"Arianna-Kinsley-Valerie","sex":"F","sociabilitate":"9","varsta":"88"}
,
{"ID":"c0x045","inaltime":"190","prenume":"Zamfir","sex":"M","sociabilitate":"10","varsta":"59"}
,
{"ID":"c0x046","inaltime":"168","prenume":"Roberta","sex":"F","sociabilitate":"5","varsta":"54"}
,
{"ID":"c0x047","inaltime":"189","prenume":"Nicodim","sex":"M","sociabilitate":"8","varsta":"18"}
,
{"ID":"c0x048","inaltime":"170","prenume":"Pavel","sex":"M","sociabilitate":"6","varsta":"37"}
,
{"ID":"c0x049","inaltime":"188","prenume":"Gratian-Elliot","sex":"M","sociabilitate":"3","varsta":"51"}
,
{"ID":"c0x050","inaltime":"170","prenume":"Serban ","sex":"M","sociabilitate":"3","varsta":"52"}
,
{"ID":"c0x051","inaltime":"189","prenume":"Romi","sex":"M","sociabilitate":"9","varsta":"35"}
,
{"ID":"c0x052","inaltime":"162","prenume":"Raluca","sex":"F","sociabilitate":"3","varsta":"66"}
,
{"ID":"c0x053","inaltime":"153","prenume":"Teresa-Daniela","sex":"F","sociabilitate":"6","varsta":"60"}
,
{"ID":"c0x054","inaltime":"188","prenume":"Dorin ","sex":"M","sociabilitate":"9","varsta":"78"}
,
{"ID":"c0x055","inaltime":"163","prenume":"Marieta","sex":"F","sociabilitate":"3","varsta":"420"}
,
{"ID":"c0x056","inaltime":"162","prenume":"Zina-Daciana-Domnica","sex":"F","sociabilitate":"7","varsta":"17"}
,
{"ID":"c0x057","inaltime":"167","prenume":"Zachary-Julian","sex":"M","sociabilitate":"9","varsta":"51"}
,
{"ID":"c0x058","inaltime":"185","prenume":"Bennett-Codrin","sex":"M","sociabilitate":"2","varsta":"48"}
,
{"ID":"c0x059","inaltime":"162","prenume":"Gabriella","sex":"F","sociabilitate":"7","varsta":"51"}
,
{"ID":"c0x060","inaltime":"176","prenume":"Emmanuel-Cedrin","sex":"M","sociabilitate":"3","varsta":"50"}
,
{"ID":"c0x061","inaltime":"178","prenume":"Nicolas-Tyler-Simion ","sex":"M","sociabilitate":"8","varsta":"60"}
,
{"ID":"c0x062","inaltime":"186","prenume":"Kayden","sex":"M","sociabilitate":"3","varsta":"70"}
,
{"ID":"c0x063","inaltime":"157","prenume":"Silvia-Sofia","sex":"F","sociabilitate":"2","varsta":"72"}
,
{"ID":"c0x064","inaltime":"167","prenume":"Consuela-Ligia","sex":"F","sociabilitate":"8","varsta":"41"}
,
{"ID":"c0x065","inaltime":"177","prenume":"Maximilian -Michael","sex":"M","sociabilitate":"2","varsta":"53"}
,
{"ID":"c0x066","inaltime":"109","prenume":"Teofil","sex":"M","sociabilitate":"6","varsta":"6"}
,
{"ID":"c0x067","inaltime":"177","prenume":"Hayden","sex":"M","sociabilitate":"6","varsta":"32"}
,
{"ID":"c0x068","inaltime":"141","prenume":"Norica","sex":"F","sociabilitate":"5","varsta":"10"}
,
{"ID":"c0x069","inaltime":"177","prenume":"Dan","sex":"M","sociabilitate":"7","varsta":"61"}
,
{"ID":"c0x070","inaltime":"159","prenume":"Ilona","sex":"F","sociabilitate":"6","varsta":"27"}
,
{"ID":"c0x071","inaltime":"185","prenume":"Theodore","sex":"M","sociabilitate":"4","varsta":"56"}
,
{"ID":"c0x072","inaltime":"174","prenume":"Dorel -Marinel","sex":"M","sociabilitate":"8","varsta":"66"}
,
{"ID":"c0x073","inaltime":"160","prenume":"Clarisa-Luminita","sex":"F","sociabilitate":"7","varsta":"25"}
,
{"ID":"c0x074","inaltime":"155","prenume":"Delilah","sex":"F","sociabilitate":"4","varsta":"73"}
,
{"ID":"c0x075","inaltime":"106","prenume":"Kylie-Angela","sex":"F","sociabilitate":"6","varsta":"4"}
,
{"ID":"c0x076","inaltime":"174","prenume":"Vincentiu","sex":"M","sociabilitate":"3","varsta":"69"}
,
{"ID":"c0x077","inaltime":"130","prenume":"Decebal ","sex":"M","sociabilitate":"8","varsta":"8"}
,
{"ID":"c0x078","inaltime":"164","prenume":"Alexandrina","sex":"F","sociabilitate":"5","varsta":"30"}
,
{"ID":"c0x079","inaltime":"185","prenume":"Lucentiu","sex":"M","sociabilitate":"7","varsta":"55"}
,
{"ID":"c0x080","inaltime":"172","prenume":"Grigoras-Banel -Sorin ","sex":"M","sociabilitate":"2","varsta":"30"}
,
{"ID":"c0x081","inaltime":"158","prenume":"Floarea-Gabriella","sex":"F","sociabilitate":"3","varsta":"32"}
,
{"ID":"c0x082","inaltime":"155","prenume":"Camelia","sex":"F","sociabilitate":"7","varsta":"39"}
,
{"ID":"c0x083","inaltime":"149","prenume":"Christian-Emanoil","sex":"M","sociabilitate":"4","varsta":"13"}
,
{"ID":"c0x084","inaltime":"172","prenume":"Amza-Giorgian","sex":"M","sociabilitate":"6","varsta":"46"}
,
{"ID":"c0x085","inaltime":"173","prenume":"Melania -Zaharia-Blakely","sex":"F","sociabilitate":"2","varsta":"52"}
,
{"ID":"c0x086","inaltime":"156","prenume":"Lydia","sex":"F","sociabilitate":"5","varsta":"59"}
,
{"ID":"c0x087","inaltime":"186","prenume":"Cezar-Xander","sex":"M","sociabilitate":"6","varsta":"76"}
,
{"ID":"c0x088","inaltime":"175","prenume":"Horatiu-Angel ","sex":"M","sociabilitate":"6","varsta":"89"}
,
{"ID":"c0x089","inaltime":"65","prenume":"Crin","sex":"M","sociabilitate":"4","varsta":"1"}
,
{"ID":"c0x090","inaltime":"173","prenume":"Artemisa","sex":"F","sociabilitate":"5","varsta":"18"}
,
{"ID":"c0x091","inaltime":"165","prenume":"Alaina","sex":"F","sociabilitate":"4","varsta":"39"}
,
{"ID":"c0x092","inaltime":"178","prenume":"Tyler","sex":"M","sociabilitate":"6","varsta":"39"}
,
{"ID":"c0x093","inaltime":"87","prenume":"Nathaniel-Ezra","sex":"M","sociabilitate":"5","varsta":"2"}
,
{"ID":"c0x094","inaltime":"173","prenume":"Gratian-Vlaicu","sex":"M","sociabilitate":"2","varsta":"41"}
,
{"ID":"c0x095","inaltime":"188","prenume":"Laurentiu","sex":"M","sociabilitate":"3","varsta":"51"}
,
{"ID":"c0x096","inaltime":"169","prenume":"Eftimie-Ilarie","sex":"M","sociabilitate":"2","varsta":"73"}
,
{"ID":"c0x097","inaltime":"165","prenume":"Scarlett","sex":"F","sociabilitate":"6","varsta":"48"}
,
{"ID":"c0x098","inaltime":"171","prenume":"Robertina","sex":"F","sociabilitate":"7","varsta":"44"}
,
{"ID":"c0x099","inaltime":"155","prenume":"Coralia-Ariana","sex":"F","sociabilitate":"7","varsta":"62"}
]
}