{
"listaNPC": [

{"ID":"c0x000","inaltime":"134","pozX":676.0,"pozY":238.0,"prenume":"Esther","sex":"F","sociabilitate":"5","varsta":"9"}
,
{"ID":"c0x001","inaltime":"179","pozX":338.0,"pozY":465.0,"prenume":"Tucker","sex":"M","sociabilitate":"7","varsta":"90"}
,
{"ID":"c0x002","inaltime":"169","pozX":913.0,"pozY":628.0,"prenume":"Vladelina","sex":"F","sociabilitate":"3","varsta":"53"}
,
{"ID":"c0x003","inaltime":"157","pozX":235.0,"pozY":626.0,"prenume":"Estera","sex":"F","sociabilitate":"5","varsta":"17"}
,
{"ID":"c0x004","inaltime":"94","pozX":762.0,"pozY":559.0,"prenume":"Ryker","sex":"M","sociabilitate":"8","varsta":"2"}
,
{"ID":"c0x005","inaltime":"108","pozX":672.0,"pozY":417.0,"prenume":"Leilani","sex":"F","sociabilitate":"8","varsta":"4"}
,
{"ID":"c0x006","inaltime":"183","pozX":108.0,"pozY":524.0,"prenume":"Aaron","sex":"M","sociabilitate":"6","varsta":"76"}
,
{"ID":"c0x007","inaltime":"155","pozX":86.0,"pozY":233.0,"prenume":"Corina","sex":"F","sociabilitate":"4","varsta":"56"}
,
{"ID":"c0x008","inaltime":"170","pozX":660.0,"pozY":97.0,"prenume":"Sofia","sex":"F","sociabilitate":"2","varsta":"33"}
,
{"ID":"c0x009","inaltime":"172","pozX":862.0,"pozY":494.0,"prenume":"Brandon","sex":"M","sociabilitate":"4","varsta":"52"}
,
{"ID":"c0x010","inaltime":"191","pozX":296.0,"pozY":527.0,"prenume":"David","sex":"M","sociabilitate":"3","varsta":"23"}
,
{"ID":"c0x011","inaltime":"183","pozX":872.0,"pozY":633.0,"prenume":"Simi -Eric ","sex":"M","sociabilitate":"6","varsta":"31"}
,
{"ID":"c0x012","inaltime":"171","pozX":579.0,"pozY":430.0,"prenume":"Ariana-Sara","sex":"F","sociabilitate":"7","varsta":"19"}
,
{"ID":"c0x013","inaltime":"50","pozX":265.0,"pozY":230.0,"prenume":"Miguel","sex":"M","sociabilitate":"6","varsta":"0"}
,
{"ID":"c0x014","inaltime":"154","pozX":822.0,"pozY":140.0,"prenume":"Brooklyn","sex":"F","sociabilitate":"8","varsta":"13"}
,
{"ID":"c0x015","inaltime":"172","pozX":580.0,"pozY":328.0,"prenume":"Isabelle-Ionela","sex":"F","sociabilitate":"6","varsta":"17"}
,
{"ID":"c0x016","inaltime":"167","pozX":675.0,"pozY":394.0,"prenume":"Anton -Brooks","sex":"M","sociabilitate":"6","varsta":"38"}
,
{"ID":"c0x017","inaltime":"182","pozX":722.0,"pozY":169.0,"prenume":"Simi -Anghel ","sex":"M","sociabilitate":"6","varsta":"42"}
,
{"ID":"c0x018","inaltime":"158","pozX":835.0,"pozY":316.0,"prenume":"Roberta","sex":"F","sociabilitate":"9","varsta":"17"}
,
{"ID":"c0x019","inaltime":"184","pozX":428.0,"pozY":437.0,"prenume":"Ciprian","sex":"M","sociabilitate":"3","varsta":"45"}
,
{"ID":"c0x020","inaltime":"176","pozX":176.0,"pozY":334.0,"prenume":"Dinu -Patru-Ionel","sex":"M","sociabilitate":"2","varsta":"80"}
,
{"ID":"c0x021","inaltime":"181","pozX":845.0,"pozY":608.0,"prenume":"Matei ","sex":"M","sociabilitate":"7","varsta":"47"}
,
{"ID":"c0x022","inaltime":"184","pozX":397.0,"pozY":89.0,"prenume":"Olimpiu","sex":"M","sociabilitate":"6","varsta":"49"}
,
{"ID":"c0x023","inaltime":"172","pozX":360.0,"pozY":551.0,"prenume":"Robert","sex":"M","sociabilitate":"8","varsta":"21"}
,
{"ID":"c0x024","inaltime":"189","pozX":180.0,"pozY":234.0,"prenume":"Norman","sex":"M","sociabilitate":"7","varsta":"23"}
,
{"ID":"c0x025","inaltime":"183","pozX":533.0,"pozY":651.0,"prenume":"Denis ","sex":"M","sociabilitate":"3","varsta":"41"}
,
{"ID":"c0x026","inaltime":"155","pozX":804.0,"pozY":582.0,"prenume":"Evelyn-Eliana","sex":"F","sociabilitate":"4","varsta":"66"}
,
{"ID":"c0x027","inaltime":"162","pozX":838.0,"pozY":647.0,"prenume":"Zamfir","sex":"M","sociabilitate":"9","varsta":"15"}
,
{"ID":"c0x028","inaltime":"158","pozX":539.0,"pozY":493.0,"prenume":"Alexia-Cornelia","sex":"F","sociabilitate":"4","varsta":"30"}
,
{"ID":"c0x029","inaltime":"128","pozX":680.0,"pozY":511.0,"prenume":"Monalisa","sex":"F","sociabilitate":"7","varsta":"8"}
,
{"ID":"c0x030","inaltime":"154","pozX":688.0,"pozY":383.0,"prenume":"Petronela-Ionuta-Dafina","sex":"F","sociabilitate":"4","varsta":"62"}
,
{"ID":"c0x031","inaltime":"179","pozX":55.0,"pozY":441.0,"prenume":"Adam","sex":"M","sociabilitate":"6","varsta":"34"}
,
{"ID":"c0x032","inaltime":"147","pozX":66.0,"pozY":238.0,"prenume":"Vlad-Max-Ladislau","sex":"M","sociabilitate":"8","varsta":"12"}
,
{"ID":"c0x033","inaltime":"152","pozX":658.0,"pozY":318.0,"prenume":"Agripina","sex":"F","sociabilitate":"4","varsta":"420"}
,
{"ID":"c0x034","inaltime":"158","pozX":460.0,"pozY":378.0,"prenume":"Daiana-Genevieve","sex":"F","sociabilitate":"7","varsta":"32"}
,
{"ID":"c0x035","inaltime":"173","pozX":478.0,"pozY":596.0,"prenume":"Evan-Wyatt-Emanuil","sex":"M","sociabilitate":"3","varsta":"51"}
,
{"ID":"c0x036","inaltime":"171","pozX":167.0,"pozY":232.0,"prenume":"Anemona ","sex":"F","sociabilitate":"9","varsta":"56"}
,
{"ID":"c0x037","inaltime":"175","pozX":121.0,"pozY":118.0,"prenume":"Mitica","sex":"M","sociabilitate":"8","varsta":"94"}
,
{"ID":"c0x038","inaltime":"85","pozX":202.0,"pozY":506.0,"prenume":"Cezar","sex":"M","sociabilitate":"4","varsta":"2"}
,
{"ID":"c0x039","inaltime":"180","pozX":572.0,"pozY":246.0,"prenume":"Razvan","sex":"M","sociabilitate":"5","varsta":"29"}
,
{"ID":"c0x040","inaltime":"172","pozX":129.0,"pozY":498.0,"prenume":"Octaviu-Nelu-Mateo","sex":"M","sociabilitate":"6","varsta":"56"}
,
{"ID":"c0x041","inaltime":"165","pozX":890.0,"pozY":331.0,"prenume":"Dana","sex":"F","sociabilitate":"5","varsta":"41"}
,
{"ID":"c0x042","inaltime":"162","pozX":182.0,"pozY":106.0,"prenume":"Georgeta","sex":"F","sociabilitate":"9","varsta":"54"}
,
{"ID":"c0x043","inaltime":"156","pozX":789.0,"pozY":680.0,"prenume":"Consuela","sex":"F","sociabilitate":"9","varsta":"60"}
,
{"ID":"c0x044","inaltime":"182","pozX":574.0,"pozY":152.0,"prenume":"Jan-Vincent","sex":"M","sociabilitate":"5","varsta":"68"}
,
{"ID":"c0x045","inaltime":"181","pozX":923.0,"pozY":117.0,"prenume":"Simion ","sex":"M","sociabilitate":"7","varsta":"26"}
,
{"ID":"c0x046","inaltime":"178","pozX":414.0,"pozY":328.0,"prenume":"Horia-Aurelian","sex":"M","sociabilitate":"6","varsta":"18"}
,
{"ID":"c0x047","inaltime":"189","pozX":100.0,"pozY":202.0,"prenume":"Vlaicu-Dorinel ","sex":"M","sociabilitate":"10","varsta":"21"}
,
{"ID":"c0x048","inaltime":"180","pozX":668.0,"pozY":651.0,"prenume":"Gicu","sex":"M","sociabilitate":"10","varsta":"62"}
,
{"ID":"c0x049","inaltime":"169","pozX":813.0,"pozY":176.0,"prenume":"Antonie-Octav-Patru","sex":"M","sociabilitate":"3","varsta":"46"}
,
{"ID":"c0x050","inaltime":"169","pozX":583.0,"pozY":565.0,"prenume":"Valentina","sex":"F","sociabilitate":"8","varsta":"85"}
,
{"ID":"c0x051","inaltime":"170","pozX":158.0,"pozY":423.0,"prenume":"Vasilichia-Gratiela","sex":"F","sociabilitate":"6","varsta":"56"}
,
{"ID":"c0x052","inaltime":"161","pozX":79.0,"pozY":669.0,"prenume":"Nadia","sex":"F","sociabilitate":"2","varsta":"42"}
,
{"ID":"c0x053","inaltime":"161","pozX":867.0,"pozY":112.0,"prenume":"Gianna","sex":"F","sociabilitate":"4","varsta":"39"}
,
{"ID":"c0x054","inaltime":"167","pozX":489.0,"pozY":555.0,"prenume":"Voicu","sex":"M","sociabilitate":"2","varsta":"30"}
,
{"ID":"c0x055","inaltime":"169","pozX":910.0,"pozY":305.0,"prenume":"Giorgiana-Arya","sex":"F","sociabilitate":"2","varsta":"50"}
,
{"ID":"c0x056","inaltime":"162","pozX":484.0,"pozY":513.0,"prenume":"Xenia","sex":"F","sociabilitate":"4","varsta":"28"}
,
{"ID":"c0x057","inaltime":"168","pozX":564.0,"pozY":635.0,"prenume":"Ayla-Arianna-Ioana","sex":"F","sociabilitate":"8","varsta":"30"}
,
{"ID":"c0x058","inaltime":"174","pozX":90.0,"pozY":414.0,"prenume":"Sara","sex":"F","sociabilitate":"9","varsta":"19"}
,
{"ID":"c0x059","inaltime":"165","pozX":685.0,"pozY":143.0,"prenume":"Anda ","sex":"F","sociabilitate":"3","varsta":"19"}
,
{"ID":"c0x060","inaltime":"157","pozX":657.0,"pozY":97.0,"prenume":"Penelope","sex":"F","sociabilitate":"8","varsta":"73"}
,
{"ID":"c0x061","inaltime":"172","pozX":384.0,"pozY":45.0,"prenume":"Jonathan","sex":"M","sociabilitate":"5","varsta":"34"}
,
{"ID":"c0x062","inaltime":"169","pozX":804.0,"pozY":667.0,"prenume":"Lili","sex":"F","sociabilitate":"9","varsta":"59"}
,
{"ID":"c0x063","inaltime":"176","pozX":423.0,"pozY":477.0,"prenume":"Matteo","sex":"M","sociabilitate":"6","varsta":"32"}
,
{"ID":"c0x064","inaltime":"182","pozX":861.0,"pozY":151.0,"prenume":"Antim ","sex":"M","sociabilitate":"2","varsta":"33"}
,
{"ID":"c0x065","inaltime":"154","pozX":211.0,"pozY":70.0,"prenume":"Daniela","sex":"F","sociabilitate":"3","varsta":"45"}
,
{"ID":"c0x066","inaltime":"158","pozX":814.0,"pozY":626.0,"prenume":"Teodosia-Florina","sex":"F","sociabilitate":"8","varsta":"63"}
,
{"ID":"c0x067","inaltime":"158","pozX":465.0,"pozY":198.0,"prenume":"Harmony","sex":"F","sociabilitate":"4","varsta":"47"}
,
{"ID":"c0x068","inaltime":"183","pozX":308.0,"pozY":469.0,"prenume":"Costica","sex":"M","sociabilitate":"5","varsta":"49"}
,
{"ID":"c0x069","inaltime":"174","pozX":702.0,"pozY":486.0,"prenume":"Kingston","sex":"M","sociabilitate":"5","varsta":"54"}
,
{"ID":"c0x070","inaltime":"161","pozX":330.0,"pozY":291.0,"prenume":"Sanziana-Evelyn","sex":"F","sociabilitate":"7","varsta":"49"}
,
{"ID":"c0x071","inaltime":"171","pozX":525.0,"pozY":232.0,"prenume":"Joita","sex":"F","sociabilitate":"2","varsta":"46"}
,
{"ID":"c0x072","inaltime":"160","pozX":323.0,"pozY":91.0,"prenume":"Flora","sex":"F","sociabilitate":"3","varsta":"42"}
,
{"ID":"c0x073","inaltime":"170","pozX":793.0,"pozY":182.0,"prenume":"Renata","sex":"F","sociabilitate":"8","varsta":"23"}
,
{"ID":"c0x074","inaltime":"175","pozX":714.0,"pozY":255.0,"prenume":"David ","sex":"M","sociabilitate":"8","varsta":"75"}
,
{"ID":"c0x075","inaltime":"174","pozX":578.0,"pozY":275.0,"prenume":"Timothy-Raul","sex":"M","sociabilitate":"5","varsta":"20"}
,
{"ID":"c0x076","inaltime":"184","pozX":65.0,"pozY":570.0,"prenume":"Casian","sex":"M","sociabilitate":"8","varsta":"33"}
,
{"ID":"c0x077","inaltime":"169","pozX":893.0,"pozY":530.0,"prenume":"Iris-Delia","sex":"F","sociabilitate":"4","varsta":"40"}
,
{"ID":"c0x078","inaltime":"177","pozX":42.0,"pozY":625.0,"prenume":"Septimiu","sex":"M","sociabilitate":"4","varsta":"57"}
,
{"ID":"c0x079","inaltime":"169","pozX":88.0,"pozY":531.0,"prenume":"Grant","sex":"M","sociabilitate":"3","varsta":"69"}
,
{"ID":"c0x080","inaltime":"170","pozX":368.0,"pozY":328.0,"prenume":"Eden","sex":"F","sociabilitate":"9","varsta":"58"}
,
{"ID":"c0x081","inaltime":"171","pozX":730.0,"pozY":367.0,"prenume":"Eusebiu","sex":"M","sociabilitate":"5","varsta":"26"}
,
{"ID":"c0x082","inaltime":"155","pozX":115.0,"pozY":367.0,"prenume":"Elisaveta ","sex":"F","sociabilitate":"2","varsta":"31"}
,
{"ID":"c0x083","inaltime":"175","pozX":324.0,"pozY":89.0,"prenume":"Alaia","sex":"F","sociabilitate":"8","varsta":"24"}
,
{"ID":"c0x084","inaltime":"169","pozX":311.0,"pozY":427.0,"prenume":"Leana","sex":"F","sociabilitate":"4","varsta":"31"}
,
{"ID":"c0x085","inaltime":"180","pozX":483.0,"pozY":579.0,"prenume":"Messiah-Jordan","sex":"M","sociabilitate":"9","varsta":"19"}
,
{"ID":"c0x086","inaltime":"169","pozX":266.0,"pozY":324.0,"prenume":"Francisc -Codrut","sex":"M","sociabilitate":"6","varsta":"57"}
,
{"ID":"c0x087","inaltime":"182","pozX":394.0,"pozY":181.0,"prenume":"Tiberiu","sex":"M","sociabilitate":"2","varsta":"44"}
,
{"ID":"c0x088","inaltime":"159","pozX":565.0,"pozY":161.0,"prenume":"Augusta","sex":"F","sociabilitate":"2","varsta":"63"}
,
{"ID":"c0x089","inaltime":"154","pozX":613.0,"pozY":503.0,"prenume":"Petruta","sex":"F","sociabilitate":"2","varsta":"31"}
,
{"ID":"c0x090","inaltime":"159","pozX":757.0,"pozY":572.0,"prenume":"Melinda -Eusebia-Anemona ","sex":"F","sociabilitate":"6","varsta":"42"}
,
{"ID":"c0x091","inaltime":"129","pozX":128.0,"pozY":127.0,"prenume":"Bentley","sex":"M","sociabilitate":"3","varsta":"8"}
,
{"ID":"c0x092","inaltime":"171","pozX":196.0,"pozY":416.0,"prenume":"Tudor","sex":"M","sociabilitate":"4","varsta":"26"}
,
{"ID":"c0x093","inaltime":"182","pozX":931.0,"pozY":313.0,"prenume":"Caius-Aurel-Barbu ","sex":"M","sociabilitate":"3","varsta":"50"}
,
{"ID":"c0x094","inaltime":"168","pozX":318.0,"pozY":592.0,"prenume":"Pamela-Sienna","sex":"F","sociabilitate":"8","varsta":"44"}
,
{"ID":"c0x095","inaltime":"170","pozX":629.0,"pozY":127.0,"prenume":"Ilie-Ryder","sex":"M","sociabilitate":"5","varsta":"58"}
,
{"ID":"c0x096","inaltime":"161","pozX":422.0,"pozY":112.0,"prenume":"Nidia-Norah","sex":"F","sociabilitate":"3","varsta":"89"}
,
{"ID":"c0x097","inaltime":"184","pozX":422.0,"pozY":623.0,"prenume":"Albert-Patru-Jonah","sex":"M","sociabilitate":"8","varsta":"40"}
,
{"ID":"c0x098","inaltime":"154","pozX":149.0,"pozY":547.0,"prenume":"Camelia-Lorelei","sex":"F","sociabilitate":"8","varsta":"28"}
,
{"ID":"c0x099","inaltime":"173","pozX":72.0,"pozY":73.0,"prenume":"Cooper","sex":"M","sociabilitate":"8","varsta":"27"}
]
}